Workbook

Sheet Modell
A1: Altersvorsorge-Modell – reale (inflationsbereinigte) Monatsrente
A2: Einmalanlage → Ansparphase → Entnahmephase. Ergebnis in heutiger Kaufkraft. Nur die blauen Felder anpassen.
A4: EINGABEN (blaue Felder)
A5: Aktuelles Alter | B5: 25
A6: Renteneintritt mit Alter | B6: 65
A7: Geld soll reichen bis Alter | B7: 90
A8: Startkapital | B8: 300000
A9: Erwartete Rendite p.a. (nominal) | B9: 0.07 | C9: optimistisch 8 % – realistisch eher 6–7 %
A10: Inflation p.a. | B10: 0.025
A11: Steuersatz auf Kapitalerträge (effektiv) | B11: 0.185 | C11: 26,375 % Abgeltungst.; Aktien-ETF mit 30 % Teilfreistellung ≈ 18,5 %
A13: ABGELEITETE GRÖSSEN
A14: Ansparjahre | B14: =B6-B5 -> 40
A15: Auszahljahre | B15: =B7-B6 -> 25
A16: Realzins p.a. (brutto) | B16: =(1+B9)/(1+B10)-1 -> 0.043902439
A17: Realzins p.a. (netto, Entnahmephase) | B17: =(1+B9*(1-B11))/(1+B10)-1 -> 0.031268293
A19: KAPITAL BEI RENTENEINTRITT
A20: Kapital nominal (brutto) | B20: =B8*(1+B9)^B14 -> 4492337.4
A21: Kapital real heute (brutto) | B21: =B8*(1+B16)^B14 -> 1673084
A22: Steuer auf Gewinn b. Entnahmebeginn | B22: =(B20-B8)*B11 -> 775582.41
A23: Kapital nominal nach Steuer | B23: =B20-(B20-B8)*B11 -> 3716754.9
A24: Kapital real heute (netto) | B24: =B23/(1+B10)^B14 -> 1384233.4
A26: MONATSRENTE (real, heutige Kaufkraft)
A27: Monatsrente brutto (vor Steuer) | B27: =B21*((1+B16)^(1/12)-1)/(1-(1+B16)^(-B15)) -> 9114.6829
A28: Monatsrente NETTO (nach Steuer) | B28: =B24*((1+B17)^(1/12)-1)/(1-(1+B17)^(-B15)) -> 6624.0269
A29: Jahresrente netto | B29: =B28*12 -> 79488.323
A30: 1. Zahlung nominal bei Renteneintritt (netto) | B30: =B28*(1+B10)^B14 -> 17785.935
A32: FAUSTREGEL (bei den aktuellen Annahmen)
A33: Je 1.000 € heute → Netto-Monatsrente (real) | B33: =B28/B8*1000 -> 22.08009 | C33: × Betrag/1.000 = deine Rente (z. B. 50.000 € → 50×)
A34: Je 1.000 € heute → Brutto-Monatsrente (real) | B34: =B27/B8*1000 -> 30.382276
A35: Umgekehrt: Kapital heute je 1.000 € gewünschte Netto-Rente/Monat | B35: =B8/B28*1000 -> 45289.671
A37: HINWEISE / ANNAHMEN
A38: • Monatliche, nachschüssige Rente; real konstant (steigt nominal mit der Inflation), Endkapital = 0 beim Endalter.
A39: • Realrechnung via Fisher: Realzins = (1+Rendite)/(1+Inflation)-1. Alle Ergebnisse in heutiger Kaufkraft.
A40: • Die Rente steigt proportional zum Startkapital – daher gilt die Faustregel für jeden Betrag.
A41: • Steuer-Näherung: Ansparphase steuerfrei wachsen, Gewinn bei Renteneintritt einmalig versteuern (ETF-Stundung), Entnahmephase laufend.
A42: • NICHT enthalten: Markt-/Reihenfolgerisiko (Crash zu Rentenbeginn), Pflege-/Gesundheitskosten, gesetzliche Rente, Gebühren.
A43: • Endalter 90 ist konservativ – wirst du jünger, bleibt ein Puffer/Erbe übrig (siehe Blatt 'Szenarien').

Sheet Betrag variabel
A1: Betrag variabel – reale Netto-Monatsrente für jeden Startbetrag
A2: Der Betrag ist die einzige echte Variable (gelb). Rendite, Inflation, Steuer & Alter kommen aus Blatt 'Modell'. Alles in heutiger Kaufkraft.
A4: DEIN SZENARIO (nur gelbe Felder ändern)
A5: Startbetrag heute (€) | B5: 300000 | C5: Rendite p.a. (Modell) | D5: =Modell!B9 -> 0.07
A6: Renteneintritt mit Alter | B6: 65 | C6: Inflation p.a. (Modell) | D6: =Modell!B10 -> 0.025
A7: Aktuelles Alter (aus 'Modell') | B7: =Modell!B5 -> 25 | C7: Steuer effektiv (Modell) | D7: =Modell!B11 -> 0.185
A8: Endalter (aus 'Modell') | B8: =Modell!B7 -> 90
A9: Ansparjahre n | B9: =B6-B7 -> 40
A10: Auszahljahre m | B10: =B8-B6 -> 25
A11: Reales Netto-Kapital bei Rente (€) | B11: =B5*(1+((1+Modell!B9)^B9-1)*(1-Modell!B11))/(1+Modell!B10)^B9 -> 1384233.4
A12: → NETTO-Monatsrente (real, heute) | B12: =B11*((1+Modell!B17)^(1/12)-1)/(1-(1+Modell!B17)^(-B10)) -> 6624.0269
A13: → Brutto-Monatsrente (real) | B13: =B5*(1+Modell!B16)^B9*((1+Modell!B16)^(1/12)-1)/(1-(1+Modell!B16)^(-B10)) -> 9114.6829
A14: → je 1.000 € heute = €/Monat netto | B14: =B12/B5*1000 -> 22.08009
A16: TABELLE 1 – NETTO-Monatsrente (real, €/Monat) je Startbetrag × Renteneintritt
A17: Startbetrag ↓ / Renteneintritt → | B17: 60 | C17: 65 | D17: 70
A18: 25000 | B18: =$A18*(1+((1+Modell!$B$9)^(B$17-Modell!$B$5)-1)*(1-Modell!$B$11))/(1+Modell!$B$10)^(B$17-Modell!$B$5)*((1+Modell!$B$17)^(1/12)-1)/(1-(1+Modell!$B$17)^(-(Modell!$B$7-B$17))) -> 398.86907 | C18: =$A18*(1+((1+Modell!$B$9)^(C$17-Modell!$B$5)-1)*(1-Modell!$B$11))/(1+Modell!$B$10)^(C$17-Modell!$B$5)*((1+Modell!$B$17)^(1/12)-1)/(1-(1+Modell!$B$17)^(-(Modell!$B$7-C$17))) -> 552.00225 | D18: =$A18*(1+((1+Modell!$B$9)^(D$17-Modell!$B$5)-1)*(1-Modell!$B$11))/(1+Modell!$B$10)^(D$17-Modell!$B$5)*((1+Modell!$B$17)^(1/12)-1)/(1-(1+Modell!$B$17)^(-(Modell!$B$7-D$17))) -> 795.58174
A19: 50000 | B19: =$A19*(1+((1+Modell!$B$9)^(B$17-Modell!$B$5)-1)*(1-Modell!$B$11))/(1+Modell!$B$10)^(B$17-Modell!$B$5)*((1+Modell!$B$17)^(1/12)-1)/(1-(1+Modell!$B$17)^(-(Modell!$B$7-B$17))) -> 797.73813 | C19: =$A19*(1+((1+Modell!$B$9)^(C$17-Modell!$B$5)-1)*(1-Modell!$B$11))/(1+Modell!$B$10)^(C$17-Modell!$B$5)*((1+Modell!$B$17)^(1/12)-1)/(1-(1+Modell!$B$17)^(-(Modell!$B$7-C$17))) -> 1104.0045 | D19: =$A19*(1+((1+Modell!$B$9)^(D$17-Modell!$B$5)-1)*(1-Modell!$B$11))/(1+Modell!$B$10)^(D$17-Modell!$B$5)*((1+Modell!$B$17)^(1/12)-1)/(1-(1+Modell!$B$17)^(-(Modell!$B$7-D$17))) -> 1591.1635
A20: 100000 | B20: =$A20*(1+((1+Modell!$B$9)^(B$17-Modell!$B$5)-1)*(1-Modell!$B$11))/(1+Modell!$B$10)^(B$17-Modell!$B$5)*((1+Modell!$B$17)^(1/12)-1)/(1-(1+Modell!$B$17)^(-(Modell!$B$7-B$17))) -> 1595.4763 | C20: =$A20*(1+((1+Modell!$B$9)^(C$17-Modell!$B$5)-1)*(1-Modell!$B$11))/(1+Modell!$B$10)^(C$17-Modell!$B$5)*((1+Modell!$B$17)^(1/12)-1)/(1-(1+Modell!$B$17)^(-(Modell!$B$7-C$17))) -> 2208.009 | D20: =$A20*(1+((1+Modell!$B$9)^(D$17-Modell!$B$5)-1)*(1-Modell!$B$11))/(1+Modell!$B$10)^(D$17-Modell!$B$5)*((1+Modell!$B$17)^(1/12)-1)/(1-(1+Modell!$B$17)^(-(Modell!$B$7-D$17))) -> 3182.3269
A21: 150000 | B21: =$A21*(1+((1+Modell!$B$9)^(B$17-Modell!$B$5)-1)*(1-Modell!$B$11))/(1+Modell!$B$10)^(B$17-Modell!$B$5)*((1+Modell!$B$17)^(1/12)-1)/(1-(1+Modell!$B$17)^(-(Modell!$B$7-B$17))) -> 2393.2144 | C21: =$A21*(1+((1+Modell!$B$9)^(C$17-Modell!$B$5)-1)*(1-Modell!$B$11))/(1+Modell!$B$10)^(C$17-Modell!$B$5)*((1+Modell!$B$17)^(1/12)-1)/(1-(1+Modell!$B$17)^(-(Modell!$B$7-C$17))) -> 3312.0135 | D21: =$A21*(1+((1+Modell!$B$9)^(D$17-Modell!$B$5)-1)*(1-Modell!$B$11))/(1+Modell!$B$10)^(D$17-Modell!$B$5)*((1+Modell!$B$17)^(1/12)-1)/(1-(1+Modell!$B$17)^(-(Modell!$B$7-D$17))) -> 4773.4904
A22: 200000 | B22: =$A22*(1+((1+Modell!$B$9)^(B$17-Modell!$B$5)-1)*(1-Modell!$B$11))/(1+Modell!$B$10)^(B$17-Modell!$B$5)*((1+Modell!$B$17)^(1/12)-1)/(1-(1+Modell!$B$17)^(-(Modell!$B$7-B$17))) -> 3190.9525 | C22: =$A22*(1+((1+Modell!$B$9)^(C$17-Modell!$B$5)-1)*(1-Modell!$B$11))/(1+Modell!$B$10)^(C$17-Modell!$B$5)*((1+Modell!$B$17)^(1/12)-1)/(1-(1+Modell!$B$17)^(-(Modell!$B$7-C$17))) -> 4416.018 | D22: =$A22*(1+((1+Modell!$B$9)^(D$17-Modell!$B$5)-1)*(1-Modell!$B$11))/(1+Modell!$B$10)^(D$17-Modell!$B$5)*((1+Modell!$B$17)^(1/12)-1)/(1-(1+Modell!$B$17)^(-(Modell!$B$7-D$17))) -> 6364.6539
A23: 300000 | B23: =$A23*(1+((1+Modell!$B$9)^(B$17-Modell!$B$5)-1)*(1-Modell!$B$11))/(1+Modell!$B$10)^(B$17-Modell!$B$5)*((1+Modell!$B$17)^(1/12)-1)/(1-(1+Modell!$B$17)^(-(Modell!$B$7-B$17))) -> 4786.4288 | C23: =$A23*(1+((1+Modell!$B$9)^(C$17-Modell!$B$5)-1)*(1-Modell!$B$11))/(1+Modell!$B$10)^(C$17-Modell!$B$5)*((1+Modell!$B$17)^(1/12)-1)/(1-(1+Modell!$B$17)^(-(Modell!$B$7-C$17))) -> 6624.0269 | D23: =$A23*(1+((1+Modell!$B$9)^(D$17-Modell!$B$5)-1)*(1-Modell!$B$11))/(1+Modell!$B$10)^(D$17-Modell!$B$5)*((1+Modell!$B$17)^(1/12)-1)/(1-(1+Modell!$B$17)^(-(Modell!$B$7-D$17))) -> 9546.9808
A24: 500000 | B24: =$A24*(1+((1+Modell!$B$9)^(B$17-Modell!$B$5)-1)*(1-Modell!$B$11))/(1+Modell!$B$10)^(B$17-Modell!$B$5)*((1+Modell!$B$17)^(1/12)-1)/(1-(1+Modell!$B$17)^(-(Modell!$B$7-B$17))) -> 7977.3813 | C24: =$A24*(1+((1+Modell!$B$9)^(C$17-Modell!$B$5)-1)*(1-Modell!$B$11))/(1+Modell!$B$10)^(C$17-Modell!$B$5)*((1+Modell!$B$17)^(1/12)-1)/(1-(1+Modell!$B$17)^(-(Modell!$B$7-C$17))) -> 11040.045 | D24: =$A24*(1+((1+Modell!$B$9)^(D$17-Modell!$B$5)-1)*(1-Modell!$B$11))/(1+Modell!$B$10)^(D$17-Modell!$B$5)*((1+Modell!$B$17)^(1/12)-1)/(1-(1+Modell!$B$17)^(-(Modell!$B$7-D$17))) -> 15911.635
A25: 750000 | B25: =$A25*(1+((1+Modell!$B$9)^(B$17-Modell!$B$5)-1)*(1-Modell!$B$11))/(1+Modell!$B$10)^(B$17-Modell!$B$5)*((1+Modell!$B$17)^(1/12)-1)/(1-(1+Modell!$B$17)^(-(Modell!$B$7-B$17))) -> 11966.072 | C25: =$A25*(1+((1+Modell!$B$9)^(C$17-Modell!$B$5)-1)*(1-Modell!$B$11))/(1+Modell!$B$10)^(C$17-Modell!$B$5)*((1+Modell!$B$17)^(1/12)-1)/(1-(1+Modell!$B$17)^(-(Modell!$B$7-C$17))) -> 16560.067 | D25: =$A25*(1+((1+Modell!$B$9)^(D$17-Modell!$B$5)-1)*(1-Modell!$B$11))/(1+Modell!$B$10)^(D$17-Modell!$B$5)*((1+Modell!$B$17)^(1/12)-1)/(1-(1+Modell!$B$17)^(-(Modell!$B$7-D$17))) -> 23867.452
A26: 1000000 | B26: =$A26*(1+((1+Modell!$B$9)^(B$17-Modell!$B$5)-1)*(1-Modell!$B$11))/(1+Modell!$B$10)^(B$17-Modell!$B$5)*((1+Modell!$B$17)^(1/12)-1)/(1-(1+Modell!$B$17)^(-(Modell!$B$7-B$17))) -> 15954.763 | C26: =$A26*(1+((1+Modell!$B$9)^(C$17-Modell!$B$5)-1)*(1-Modell!$B$11))/(1+Modell!$B$10)^(C$17-Modell!$B$5)*((1+Modell!$B$17)^(1/12)-1)/(1-(1+Modell!$B$17)^(-(Modell!$B$7-C$17))) -> 22080.09 | D26: =$A26*(1+((1+Modell!$B$9)^(D$17-Modell!$B$5)-1)*(1-Modell!$B$11))/(1+Modell!$B$10)^(D$17-Modell!$B$5)*((1+Modell!$B$17)^(1/12)-1)/(1-(1+Modell!$B$17)^(-(Modell!$B$7-D$17))) -> 31823.269
A27: 1500000 | B27: =$A27*(1+((1+Modell!$B$9)^(B$17-Modell!$B$5)-1)*(1-Modell!$B$11))/(1+Modell!$B$10)^(B$17-Modell!$B$5)*((1+Modell!$B$17)^(1/12)-1)/(1-(1+Modell!$B$17)^(-(Modell!$B$7-B$17))) -> 23932.144 | C27: =$A27*(1+((1+Modell!$B$9)^(C$17-Modell!$B$5)-1)*(1-Modell!$B$11))/(1+Modell!$B$10)^(C$17-Modell!$B$5)*((1+Modell!$B$17)^(1/12)-1)/(1-(1+Modell!$B$17)^(-(Modell!$B$7-C$17))) -> 33120.135 | D27: =$A27*(1+((1+Modell!$B$9)^(D$17-Modell!$B$5)-1)*(1-Modell!$B$11))/(1+Modell!$B$10)^(D$17-Modell!$B$5)*((1+Modell!$B$17)^(1/12)-1)/(1-(1+Modell!$B$17)^(-(Modell!$B$7-D$17))) -> 47734.904
A28: 2000000 | B28: =$A28*(1+((1+Modell!$B$9)^(B$17-Modell!$B$5)-1)*(1-Modell!$B$11))/(1+Modell!$B$10)^(B$17-Modell!$B$5)*((1+Modell!$B$17)^(1/12)-1)/(1-(1+Modell!$B$17)^(-(Modell!$B$7-B$17))) -> 31909.525 | C28: =$A28*(1+((1+Modell!$B$9)^(C$17-Modell!$B$5)-1)*(1-Modell!$B$11))/(1+Modell!$B$10)^(C$17-Modell!$B$5)*((1+Modell!$B$17)^(1/12)-1)/(1-(1+Modell!$B$17)^(-(Modell!$B$7-C$17))) -> 44160.18 | D28: =$A28*(1+((1+Modell!$B$9)^(D$17-Modell!$B$5)-1)*(1-Modell!$B$11))/(1+Modell!$B$10)^(D$17-Modell!$B$5)*((1+Modell!$B$17)^(1/12)-1)/(1-(1+Modell!$B$17)^(-(Modell!$B$7-D$17))) -> 63646.539
A30: TABELLE 2 – UMGEKEHRT: nötiger Startbetrag heute (€) für Wunsch-Netto-Rente
A31: Wunsch €/Mon ↓ / Renteneintritt → | B31: 60 | C31: 65 | D31: 70
A32: 1000 | B32: =$A32/((1+((1+Modell!$B$9)^(B$31-Modell!$B$5)-1)*(1-Modell!$B$11))/(1+Modell!$B$10)^(B$31-Modell!$B$5)*((1+Modell!$B$17)^(1/12)-1)/(1-(1+Modell!$B$17)^(-(Modell!$B$7-B$31)))) -> 62677.209 | C32: =$A32/((1+((1+Modell!$B$9)^(C$31-Modell!$B$5)-1)*(1-Modell!$B$11))/(1+Modell!$B$10)^(C$31-Modell!$B$5)*((1+Modell!$B$17)^(1/12)-1)/(1-(1+Modell!$B$17)^(-(Modell!$B$7-C$31)))) -> 45289.671 | D32: =$A32/((1+((1+Modell!$B$9)^(D$31-Modell!$B$5)-1)*(1-Modell!$B$11))/(1+Modell!$B$10)^(D$31-Modell!$B$5)*((1+Modell!$B$17)^(1/12)-1)/(1-(1+Modell!$B$17)^(-(Modell!$B$7-D$31)))) -> 31423.547
A33: 2000 | B33: =$A33/((1+((1+Modell!$B$9)^(B$31-Modell!$B$5)-1)*(1-Modell!$B$11))/(1+Modell!$B$10)^(B$31-Modell!$B$5)*((1+Modell!$B$17)^(1/12)-1)/(1-(1+Modell!$B$17)^(-(Modell!$B$7-B$31)))) -> 125354.42 | C33: =$A33/((1+((1+Modell!$B$9)^(C$31-Modell!$B$5)-1)*(1-Modell!$B$11))/(1+Modell!$B$10)^(C$31-Modell!$B$5)*((1+Modell!$B$17)^(1/12)-1)/(1-(1+Modell!$B$17)^(-(Modell!$B$7-C$31)))) -> 90579.342 | D33: =$A33/((1+((1+Modell!$B$9)^(D$31-Modell!$B$5)-1)*(1-Modell!$B$11))/(1+Modell!$B$10)^(D$31-Modell!$B$5)*((1+Modell!$B$17)^(1/12)-1)/(1-(1+Modell!$B$17)^(-(Modell!$B$7-D$31)))) -> 62847.094
A34: 3000 | B34: =$A34/((1+((1+Modell!$B$9)^(B$31-Modell!$B$5)-1)*(1-Modell!$B$11))/(1+Modell!$B$10)^(B$31-Modell!$B$5)*((1+Modell!$B$17)^(1/12)-1)/(1-(1+Modell!$B$17)^(-(Modell!$B$7-B$31)))) -> 188031.63 | C34: =$A34/((1+((1+Modell!$B$9)^(C$31-Modell!$B$5)-1)*(1-Modell!$B$11))/(1+Modell!$B$10)^(C$31-Modell!$B$5)*((1+Modell!$B$17)^(1/12)-1)/(1-(1+Modell!$B$17)^(-(Modell!$B$7-C$31)))) -> 135869.01 | D34: =$A34/((1+((1+Modell!$B$9)^(D$31-Modell!$B$5)-1)*(1-Modell!$B$11))/(1+Modell!$B$10)^(D$31-Modell!$B$5)*((1+Modell!$B$17)^(1/12)-1)/(1-(1+Modell!$B$17)^(-(Modell!$B$7-D$31)))) -> 94270.641
A35: 5000 | B35: =$A35/((1+((1+Modell!$B$9)^(B$31-Modell!$B$5)-1)*(1-Modell!$B$11))/(1+Modell!$B$10)^(B$31-Modell!$B$5)*((1+Modell!$B$17)^(1/12)-1)/(1-(1+Modell!$B$17)^(-(Modell!$B$7-B$31)))) -> 313386.05 | C35: =$A35/((1+((1+Modell!$B$9)^(C$31-Modell!$B$5)-1)*(1-Modell!$B$11))/(1+Modell!$B$10)^(C$31-Modell!$B$5)*((1+Modell!$B$17)^(1/12)-1)/(1-(1+Modell!$B$17)^(-(Modell!$B$7-C$31)))) -> 226448.35 | D35: =$A35/((1+((1+Modell!$B$9)^(D$31-Modell!$B$5)-1)*(1-Modell!$B$11))/(1+Modell!$B$10)^(D$31-Modell!$B$5)*((1+Modell!$B$17)^(1/12)-1)/(1-(1+Modell!$B$17)^(-(Modell!$B$7-D$31)))) -> 157117.73
A37: HINWEISE
A38: • Der Betrag skaliert die Rente LINEAR: doppelter Betrag = doppelte Rente (deshalb reicht eine Tabelle für alle Fälle).
A39: • Annahmen (Rendite, Inflation, Steuer, aktuelles Alter, Endalter) stammen aus Blatt 'Modell' – dort ändern wirkt hier automatisch.
A40: • Renteneintritt in den Tabellen fest 60/65/70; im Szenario oben frei wählbar. Auszahlung bis Endkapital 0 beim Endalter.
A41: • Alle Beträge real (heutige Kaufkraft). Steuer: ETF-Stundung, Gewinn bei Renteneintritt versteuert, Entnahme laufend.

Sheet Ewige Rente
A1: Ewige Rente – von den Erträgen leben, Kapital bleibt erhalten
A2: Du entnimmst jährlich einen festen %-Satz; liegt er unter der Realrendite, wächst das Kapital real weiter. Nur blaue Felder ändern.
A4: ANNAHMEN (blaue Felder)
A5: Startkapital | B5: 300000
A6: Rendite p.a. nominal | B6: 0.07
A7: Inflation p.a. | B7: 0.025
A8: Entnahmequote (sicher) p.a. | B8: 0.035 | C8: klassisch 3–4 % ('Safe Withdrawal Rate')
A9: Steuersatz auf Erträge (effektiv) | B9: 0.185
A11: Realzins p.a. (brutto) | B11: =(1+B6)/(1+B7)-1 -> 0.043902439
A12: Kapital wächst real um (Realzins − Entnahme) | B12: =B11-B8 -> 0.008902439 | C12: positiv = ewig (Kapital wächst); negativ = schrumpft, nicht ewig
A14: TABELLE 1 – Ewige Rente nach Anspardauer (bei den aktuellen Annahmen)
A15: Anspardauer (Jahre) | B15: Reales Kapital heute (€) | C15: Ewige Rente BRUTTO (€/Mon) | D15: Ewige Rente NETTO (€/Mon) | E15: je 1.000 € netto (€/Mon)
A16: 5 | B16: =$B$5*((1+$B$6)/(1+$B$7))^A16 -> 371895.41 | C16: =B16*$B$8/12 -> 1084.6949 | D16: =C16*(1-$B$9) -> 884.02638 | E16: =D16/$B$5*1000 -> 2.9467546
A17: 10 | B17: =$B$5*((1+$B$6)/(1+$B$7))^A17 -> 461020.65 | C17: =B17*$B$8/12 -> 1344.6436 | D17: =C17*(1-$B$9) -> 1095.8845 | E17: =D17/$B$5*1000 -> 3.6529483
A18: 15 | B18: =$B$5*((1+$B$6)/(1+$B$7))^A18 -> 571504.87 | C18: =B18*$B$8/12 -> 1666.8892 | D18: =C18*(1-$B$9) -> 1358.5147 | E18: =D18/$B$5*1000 -> 4.5283824
A19: 20 | B19: =$B$5*((1+$B$6)/(1+$B$7))^A19 -> 708466.8 | C19: =B19*$B$8/12 -> 2066.3615 | D19: =C19*(1-$B$9) -> 1684.0846 | E19: =D19/$B$5*1000 -> 5.6136154
A20: 25 | B20: =$B$5*((1+$B$6)/(1+$B$7))^A20 -> 878251.83 | C20: =B20*$B$8/12 -> 2561.5678 | D20: =C20*(1-$B$9) -> 2087.6778 | E20: =D20/$B$5*1000 -> 6.9589259
A21: 30 | B21: =$B$5*((1+$B$6)/(1+$B$7))^A21 -> 1088726.1 | C21: =B21*$B$8/12 -> 3175.451 | D21: =C21*(1-$B$9) -> 2587.9926 | E21: =D21/$B$5*1000 -> 8.626642
A22: 35 | B22: =$B$5*((1+$B$6)/(1+$B$7))^A22 -> 1349640.8 | C22: =B22*$B$8/12 -> 3936.4522 | D22: =C22*(1-$B$9) -> 3208.2086 | E22: =D22/$B$5*1000 -> 10.694029
A23: 40 | B23: =$B$5*((1+$B$6)/(1+$B$7))^A23 -> 1673084 | C23: =B23*$B$8/12 -> 4879.8283 | D23: =C23*(1-$B$9) -> 3977.0601 | E23: =D23/$B$5*1000 -> 13.256867
A24: 45 | B24: =$B$5*((1+$B$6)/(1+$B$7))^A24 -> 2074040.9 | C24: =B24*$B$8/12 -> 6049.2858 | D24: =C24*(1-$B$9) -> 4930.168 | E24: =D24/$B$5*1000 -> 16.433893
A26: TABELLE 2 – Netto €/Monat nach Entnahmequote × Anspardauer (für Startkapital)
A27: Anspardauer ↓ / Entnahme → | B27: 0.03 | C27: 0.035 | D27: 0.04 | E27: 0.045
A28: 20 | B28: =$B$5*((1+$B$6)/(1+$B$7))^$A28*B$27/12*(1-$B$9) -> 1443.5011 | C28: =$B$5*((1+$B$6)/(1+$B$7))^$A28*C$27/12*(1-$B$9) -> 1684.0846 | D28: =$B$5*((1+$B$6)/(1+$B$7))^$A28*D$27/12*(1-$B$9) -> 1924.6681 | E28: =$B$5*((1+$B$6)/(1+$B$7))^$A28*E$27/12*(1-$B$9) -> 2165.2516
A29: 25 | B29: =$B$5*((1+$B$6)/(1+$B$7))^$A29*B$27/12*(1-$B$9) -> 1789.4381 | C29: =$B$5*((1+$B$6)/(1+$B$7))^$A29*C$27/12*(1-$B$9) -> 2087.6778 | D29: =$B$5*((1+$B$6)/(1+$B$7))^$A29*D$27/12*(1-$B$9) -> 2385.9175 | E29: =$B$5*((1+$B$6)/(1+$B$7))^$A29*E$27/12*(1-$B$9) -> 2684.1571
A30: 30 | B30: =$B$5*((1+$B$6)/(1+$B$7))^$A30*B$27/12*(1-$B$9) -> 2218.2794 | C30: =$B$5*((1+$B$6)/(1+$B$7))^$A30*C$27/12*(1-$B$9) -> 2587.9926 | D30: =$B$5*((1+$B$6)/(1+$B$7))^$A30*D$27/12*(1-$B$9) -> 2957.7058 | E30: =$B$5*((1+$B$6)/(1+$B$7))^$A30*E$27/12*(1-$B$9) -> 3327.4191
A31: 35 | B31: =$B$5*((1+$B$6)/(1+$B$7))^$A31*B$27/12*(1-$B$9) -> 2749.893 | C31: =$B$5*((1+$B$6)/(1+$B$7))^$A31*C$27/12*(1-$B$9) -> 3208.2086 | D31: =$B$5*((1+$B$6)/(1+$B$7))^$A31*D$27/12*(1-$B$9) -> 3666.5241 | E31: =$B$5*((1+$B$6)/(1+$B$7))^$A31*E$27/12*(1-$B$9) -> 4124.8396
A32: 40 | B32: =$B$5*((1+$B$6)/(1+$B$7))^$A32*B$27/12*(1-$B$9) -> 3408.9087 | C32: =$B$5*((1+$B$6)/(1+$B$7))^$A32*C$27/12*(1-$B$9) -> 3977.0601 | D32: =$B$5*((1+$B$6)/(1+$B$7))^$A32*D$27/12*(1-$B$9) -> 4545.2115 | E32: =$B$5*((1+$B$6)/(1+$B$7))^$A32*E$27/12*(1-$B$9) -> 5113.363
A33: 45 | B33: =$B$5*((1+$B$6)/(1+$B$7))^$A33*B$27/12*(1-$B$9) -> 4225.8583 | C33: =$B$5*((1+$B$6)/(1+$B$7))^$A33*C$27/12*(1-$B$9) -> 4930.168 | D33: =$B$5*((1+$B$6)/(1+$B$7))^$A33*D$27/12*(1-$B$9) -> 5634.4777 | E33: =$B$5*((1+$B$6)/(1+$B$7))^$A33*E$27/12*(1-$B$9) -> 6338.7874
A34: Kapital wächst real/Jahr → | B34: =$B$11-B$27 -> 0.013902439 | C34: =$B$11-C$27 -> 0.008902439 | D34: =$B$11-D$27 -> 0.003902439 | E34: =$B$11-E$27 -> -0.001097561
A35: Negativ ⇒ Entnahme über Realrendite ⇒ Kapital schrumpft, NICHT mehr ewig.
A37: HINWEISE
A38: • Reales Kapital = Startkapital × (1,07/1,025)^n (Ansparphase, brutto/buy-and-hold).
A39: • Ewige Rente = Entnahmequote × reales Kapital; bleibt real konstant, solange Quote ≤ Realrendite.
A40: • Steuer: Entnahmen mit effektivem Satz auf Erträge versteuert (netto = brutto × (1−Steuer)).
A41: • 'Ewig' gilt nur, wenn Entnahmequote < Realrendite (hier 4,39 %). Darüber wird Kapital aufgezehrt.
A42: • Kein Markt-/Reihenfolgerisiko abgebildet – der Puffer (Realrendite − Entnahme) ist genau dafür da.

Sheet Szenarien
A1: Szenario-Matrix – reale Monatsrente (heutige Kaufkraft)
A2: Basis aus Blatt 'Modell': Startkapital, Ansparjahre, Inflation, Steuersatz, Renteneintritt. Spalten = Rendite p.a. nominal, Zeilen = Endalter.
A4: NETTO (nach Steuer) – € real / Monat
A5: Geld reicht bis Alter | B5: Auszahljahre | C5: 0.05 | D5: 0.06 | E5: 0.07 | F5: 0.08
A6: 85 | B6: =A6-Modell!$B$6 -> 20 | C6: =((((Modell!$B$8*(1+C$5)^Modell!$B$14)-((Modell!$B$8*(1+C$5)^Modell!$B$14)-Modell!$B$8)*Modell!$B$11)/(1+Modell!$B$10)^Modell!$B$14))*((1+((1+C$5*(1-Modell!$B$11))/(1+Modell!$B$10)-1))^(1/12)-1)/(1-(1+((1+C$5*(1-Modell!$B$11))/(1+Modell!$B$10)-1))^(-($A6-Modell!$B$6))) -> 3201.0084 | D6: =((((Modell!$B$8*(1+D$5)^Modell!$B$14)-((Modell!$B$8*(1+D$5)^Modell!$B$14)-Modell!$B$8)*Modell!$B$11)/(1+Modell!$B$10)^Modell!$B$14))*((1+((1+D$5*(1-Modell!$B$11))/(1+Modell!$B$10)-1))^(1/12)-1)/(1-(1+((1+D$5*(1-Modell!$B$11))/(1+Modell!$B$10)-1))^(-($A6-Modell!$B$6))) -> 4983.2012 | E6: =((((Modell!$B$8*(1+E$5)^Modell!$B$14)-((Modell!$B$8*(1+E$5)^Modell!$B$14)-Modell!$B$8)*Modell!$B$11)/(1+Modell!$B$10)^Modell!$B$14))*((1+((1+E$5*(1-Modell!$B$11))/(1+Modell!$B$10)-1))^(1/12)-1)/(1-(1+((1+E$5*(1-Modell!$B$11))/(1+Modell!$B$10)-1))^(-($A6-Modell!$B$6))) -> 7734.4919 | F6: =((((Modell!$B$8*(1+F$5)^Modell!$B$14)-((Modell!$B$8*(1+F$5)^Modell!$B$14)-Modell!$B$8)*Modell!$B$11)/(1+Modell!$B$10)^Modell!$B$14))*((1+((1+F$5*(1-Modell!$B$11))/(1+Modell!$B$10)-1))^(1/12)-1)/(1-(1+((1+F$5*(1-Modell!$B$11))/(1+Modell!$B$10)-1))^(-($A6-Modell!$B$6))) -> 11958.782
A7: 90 | B7: =A7-Modell!$B$6 -> 25 | C7: =((((Modell!$B$8*(1+C$5)^Modell!$B$14)-((Modell!$B$8*(1+C$5)^Modell!$B$14)-Modell!$B$8)*Modell!$B$11)/(1+Modell!$B$10)^Modell!$B$14))*((1+((1+C$5*(1-Modell!$B$11))/(1+Modell!$B$10)-1))^(1/12)-1)/(1-(1+((1+C$5*(1-Modell!$B$11))/(1+Modell!$B$10)-1))^(-($A7-Modell!$B$6))) -> 2654.5341 | D7: =((((Modell!$B$8*(1+D$5)^Modell!$B$14)-((Modell!$B$8*(1+D$5)^Modell!$B$14)-Modell!$B$8)*Modell!$B$11)/(1+Modell!$B$10)^Modell!$B$14))*((1+((1+D$5*(1-Modell!$B$11))/(1+Modell!$B$10)-1))^(1/12)-1)/(1-(1+((1+D$5*(1-Modell!$B$11))/(1+Modell!$B$10)-1))^(-($A7-Modell!$B$6))) -> 4202.141 | E7: =((((Modell!$B$8*(1+E$5)^Modell!$B$14)-((Modell!$B$8*(1+E$5)^Modell!$B$14)-Modell!$B$8)*Modell!$B$11)/(1+Modell!$B$10)^Modell!$B$14))*((1+((1+E$5*(1-Modell!$B$11))/(1+Modell!$B$10)-1))^(1/12)-1)/(1-(1+((1+E$5*(1-Modell!$B$11))/(1+Modell!$B$10)-1))^(-($A7-Modell!$B$6))) -> 6624.0269 | F7: =((((Modell!$B$8*(1+F$5)^Modell!$B$14)-((Modell!$B$8*(1+F$5)^Modell!$B$14)-Modell!$B$8)*Modell!$B$11)/(1+Modell!$B$10)^Modell!$B$14))*((1+((1+F$5*(1-Modell!$B$11))/(1+Modell!$B$10)-1))^(1/12)-1)/(1-(1+((1+F$5*(1-Modell!$B$11))/(1+Modell!$B$10)-1))^(-($A7-Modell!$B$6))) -> 10389.494
A8: 95 | B8: =A8-Modell!$B$6 -> 30 | C8: =((((Modell!$B$8*(1+C$5)^Modell!$B$14)-((Modell!$B$8*(1+C$5)^Modell!$B$14)-Modell!$B$8)*Modell!$B$11)/(1+Modell!$B$10)^Modell!$B$14))*((1+((1+C$5*(1-Modell!$B$11))/(1+Modell!$B$10)-1))^(1/12)-1)/(1-(1+((1+C$5*(1-Modell!$B$11))/(1+Modell!$B$10)-1))^(-($A8-Modell!$B$6))) -> 2291.9741 | D8: =((((Modell!$B$8*(1+D$5)^Modell!$B$14)-((Modell!$B$8*(1+D$5)^Modell!$B$14)-Modell!$B$8)*Modell!$B$11)/(1+Modell!$B$10)^Modell!$B$14))*((1+((1+D$5*(1-Modell!$B$11))/(1+Modell!$B$10)-1))^(1/12)-1)/(1-(1+((1+D$5*(1-Modell!$B$11))/(1+Modell!$B$10)-1))^(-($A8-Modell!$B$6))) -> 3687.1332 | E8: =((((Modell!$B$8*(1+E$5)^Modell!$B$14)-((Modell!$B$8*(1+E$5)^Modell!$B$14)-Modell!$B$8)*Modell!$B$11)/(1+Modell!$B$10)^Modell!$B$14))*((1+((1+E$5*(1-Modell!$B$11))/(1+Modell!$B$10)-1))^(1/12)-1)/(1-(1+((1+E$5*(1-Modell!$B$11))/(1+Modell!$B$10)-1))^(-($A8-Modell!$B$6))) -> 5898.0495 | F8: =((((Modell!$B$8*(1+F$5)^Modell!$B$14)-((Modell!$B$8*(1+F$5)^Modell!$B$14)-Modell!$B$8)*Modell!$B$11)/(1+Modell!$B$10)^Modell!$B$14))*((1+((1+F$5*(1-Modell!$B$11))/(1+Modell!$B$10)-1))^(1/12)-1)/(1-(1+((1+F$5*(1-Modell!$B$11))/(1+Modell!$B$10)-1))^(-($A8-Modell!$B$6))) -> 9374.576
A9: 100 | B9: =A9-Modell!$B$6 -> 35 | C9: =((((Modell!$B$8*(1+C$5)^Modell!$B$14)-((Modell!$B$8*(1+C$5)^Modell!$B$14)-Modell!$B$8)*Modell!$B$11)/(1+Modell!$B$10)^Modell!$B$14))*((1+((1+C$5*(1-Modell!$B$11))/(1+Modell!$B$10)-1))^(1/12)-1)/(1-(1+((1+C$5*(1-Modell!$B$11))/(1+Modell!$B$10)-1))^(-($A9-Modell!$B$6))) -> 2034.4985 | D9: =((((Modell!$B$8*(1+D$5)^Modell!$B$14)-((Modell!$B$8*(1+D$5)^Modell!$B$14)-Modell!$B$8)*Modell!$B$11)/(1+Modell!$B$10)^Modell!$B$14))*((1+((1+D$5*(1-Modell!$B$11))/(1+Modell!$B$10)-1))^(1/12)-1)/(1-(1+((1+D$5*(1-Modell!$B$11))/(1+Modell!$B$10)-1))^(-($A9-Modell!$B$6))) -> 3324.0851 | E9: =((((Modell!$B$8*(1+E$5)^Modell!$B$14)-((Modell!$B$8*(1+E$5)^Modell!$B$14)-Modell!$B$8)*Modell!$B$11)/(1+Modell!$B$10)^Modell!$B$14))*((1+((1+E$5*(1-Modell!$B$11))/(1+Modell!$B$10)-1))^(1/12)-1)/(1-(1+((1+E$5*(1-Modell!$B$11))/(1+Modell!$B$10)-1))^(-($A9-Modell!$B$6))) -> 5391.4675 | F9: =((((Modell!$B$8*(1+F$5)^Modell!$B$14)-((Modell!$B$8*(1+F$5)^Modell!$B$14)-Modell!$B$8)*Modell!$B$11)/(1+Modell!$B$10)^Modell!$B$14))*((1+((1+F$5*(1-Modell!$B$11))/(1+Modell!$B$10)-1))^(1/12)-1)/(1-(1+((1+F$5*(1-Modell!$B$11))/(1+Modell!$B$10)-1))^(-($A9-Modell!$B$6))) -> 8675.3954
A10: 105 | B10: =A10-Modell!$B$6 -> 40 | C10: =((((Modell!$B$8*(1+C$5)^Modell!$B$14)-((Modell!$B$8*(1+C$5)^Modell!$B$14)-Modell!$B$8)*Modell!$B$11)/(1+Modell!$B$10)^Modell!$B$14))*((1+((1+C$5*(1-Modell!$B$11))/(1+Modell!$B$10)-1))^(1/12)-1)/(1-(1+((1+C$5*(1-Modell!$B$11))/(1+Modell!$B$10)-1))^(-($A10-Modell!$B$6))) -> 1842.6907 | D10: =((((Modell!$B$8*(1+D$5)^Modell!$B$14)-((Modell!$B$8*(1+D$5)^Modell!$B$14)-Modell!$B$8)*Modell!$B$11)/(1+Modell!$B$10)^Modell!$B$14))*((1+((1+D$5*(1-Modell!$B$11))/(1+Modell!$B$10)-1))^(1/12)-1)/(1-(1+((1+D$5*(1-Modell!$B$11))/(1+Modell!$B$10)-1))^(-($A10-Modell!$B$6))) -> 3055.9404 | E10: =((((Modell!$B$8*(1+E$5)^Modell!$B$14)-((Modell!$B$8*(1+E$5)^Modell!$B$14)-Modell!$B$8)*Modell!$B$11)/(1+Modell!$B$10)^Modell!$B$14))*((1+((1+E$5*(1-Modell!$B$11))/(1+Modell!$B$10)-1))^(1/12)-1)/(1-(1+((1+E$5*(1-Modell!$B$11))/(1+Modell!$B$10)-1))^(-($A10-Modell!$B$6))) -> 5021.696 | F10: =((((Modell!$B$8*(1+F$5)^Modell!$B$14)-((Modell!$B$8*(1+F$5)^Modell!$B$14)-Modell!$B$8)*Modell!$B$11)/(1+Modell!$B$10)^Modell!$B$14))*((1+((1+F$5*(1-Modell!$B$11))/(1+Modell!$B$10)-1))^(1/12)-1)/(1-(1+((1+F$5*(1-Modell!$B$11))/(1+Modell!$B$10)-1))^(-($A10-Modell!$B$6))) -> 8172.5234
A12: BRUTTO (vor Steuer) – € real / Monat
A13: Geld reicht bis Alter | B13: Auszahljahre | C13: 0.05 | D13: 0.06 | E13: 0.07 | F13: 0.08
A14: 85 | B14: =A14-Modell!$B$6 -> 20 | C14: =((Modell!$B$8*(1+((1+C$13)/(1+Modell!$B$10)-1))^Modell!$B$14))*((1+((1+C$13)/(1+Modell!$B$10)-1))^(1/12)-1)/(1-(1+((1+C$13)/(1+Modell!$B$10)-1))^(-($A14-Modell!$B$6))) -> 4134.4976 | D14: =((Modell!$B$8*(1+((1+D$13)/(1+Modell!$B$10)-1))^Modell!$B$14))*((1+((1+D$13)/(1+Modell!$B$10)-1))^(1/12)-1)/(1-(1+((1+D$13)/(1+Modell!$B$10)-1))^(-($A14-Modell!$B$6))) -> 6583.9727 | E14: =((Modell!$B$8*(1+((1+E$13)/(1+Modell!$B$10)-1))^Modell!$B$14))*((1+((1+E$13)/(1+Modell!$B$10)-1))^(1/12)-1)/(1-(1+((1+E$13)/(1+Modell!$B$10)-1))^(-($A14-Modell!$B$6))) -> 10408.838 | F14: =((Modell!$B$8*(1+((1+F$13)/(1+Modell!$B$10)-1))^Modell!$B$14))*((1+((1+F$13)/(1+Modell!$B$10)-1))^(1/12)-1)/(1-(1+((1+F$13)/(1+Modell!$B$10)-1))^(-($A14-Modell!$B$6))) -> 16340.033
A15: 90 | B15: =A15-Modell!$B$6 -> 25 | C15: =((Modell!$B$8*(1+((1+C$13)/(1+Modell!$B$10)-1))^Modell!$B$14))*((1+((1+C$13)/(1+Modell!$B$10)-1))^(1/12)-1)/(1-(1+((1+C$13)/(1+Modell!$B$10)-1))^(-($A15-Modell!$B$6))) -> 3494.0062 | D15: =((Modell!$B$8*(1+((1+D$13)/(1+Modell!$B$10)-1))^Modell!$B$14))*((1+((1+D$13)/(1+Modell!$B$10)-1))^(1/12)-1)/(1-(1+((1+D$13)/(1+Modell!$B$10)-1))^(-($A15-Modell!$B$6))) -> 5668.7396 | E15: =((Modell!$B$8*(1+((1+E$13)/(1+Modell!$B$10)-1))^Modell!$B$14))*((1+((1+E$13)/(1+Modell!$B$10)-1))^(1/12)-1)/(1-(1+((1+E$13)/(1+Modell!$B$10)-1))^(-($A15-Modell!$B$6))) -> 9114.6829 | F15: =((Modell!$B$8*(1+((1+F$13)/(1+Modell!$B$10)-1))^Modell!$B$14))*((1+((1+F$13)/(1+Modell!$B$10)-1))^(1/12)-1)/(1-(1+((1+F$13)/(1+Modell!$B$10)-1))^(-($A15-Modell!$B$6))) -> 14528.487
A16: 95 | B16: =A16-Modell!$B$6 -> 30 | C16: =((Modell!$B$8*(1+((1+C$13)/(1+Modell!$B$10)-1))^Modell!$B$14))*((1+((1+C$13)/(1+Modell!$B$10)-1))^(1/12)-1)/(1-(1+((1+C$13)/(1+Modell!$B$10)-1))^(-($A16-Modell!$B$6))) -> 3072.1146 | D16: =((Modell!$B$8*(1+((1+D$13)/(1+Modell!$B$10)-1))^Modell!$B$14))*((1+((1+D$13)/(1+Modell!$B$10)-1))^(1/12)-1)/(1-(1+((1+D$13)/(1+Modell!$B$10)-1))^(-($A16-Modell!$B$6))) -> 5072.58 | E16: =((Modell!$B$8*(1+((1+E$13)/(1+Modell!$B$10)-1))^Modell!$B$14))*((1+((1+E$13)/(1+Modell!$B$10)-1))^(1/12)-1)/(1-(1+((1+E$13)/(1+Modell!$B$10)-1))^(-($A16-Modell!$B$6))) -> 8283.8446 | F16: =((Modell!$B$8*(1+((1+F$13)/(1+Modell!$B$10)-1))^Modell!$B$14))*((1+((1+F$13)/(1+Modell!$B$10)-1))^(1/12)-1)/(1-(1+((1+F$13)/(1+Modell!$B$10)-1))^(-($A16-Modell!$B$6))) -> 13385.766
A17: 100 | B17: =A17-Modell!$B$6 -> 35 | C17: =((Modell!$B$8*(1+((1+C$13)/(1+Modell!$B$10)-1))^Modell!$B$14))*((1+((1+C$13)/(1+Modell!$B$10)-1))^(1/12)-1)/(1-(1+((1+C$13)/(1+Modell!$B$10)-1))^(-($A17-Modell!$B$6))) -> 2775.0686 | D17: =((Modell!$B$8*(1+((1+D$13)/(1+Modell!$B$10)-1))^Modell!$B$14))*((1+((1+D$13)/(1+Modell!$B$10)-1))^(1/12)-1)/(1-(1+((1+D$13)/(1+Modell!$B$10)-1))^(-($A17-Modell!$B$6))) -> 4658.3879 | E17: =((Modell!$B$8*(1+((1+E$13)/(1+Modell!$B$10)-1))^Modell!$B$14))*((1+((1+E$13)/(1+Modell!$B$10)-1))^(1/12)-1)/(1-(1+((1+E$13)/(1+Modell!$B$10)-1))^(-($A17-Modell!$B$6))) -> 7716.4405 | F17: =((Modell!$B$8*(1+((1+F$13)/(1+Modell!$B$10)-1))^Modell!$B$14))*((1+((1+F$13)/(1+Modell!$B$10)-1))^(1/12)-1)/(1-(1+((1+F$13)/(1+Modell!$B$10)-1))^(-($A17-Modell!$B$6))) -> 12621.357
A18: 105 | B18: =A18-Modell!$B$6 -> 40 | C18: =((Modell!$B$8*(1+((1+C$13)/(1+Modell!$B$10)-1))^Modell!$B$14))*((1+((1+C$13)/(1+Modell!$B$10)-1))^(1/12)-1)/(1-(1+((1+C$13)/(1+Modell!$B$10)-1))^(-($A18-Modell!$B$6))) -> 2555.9815 | D18: =((Modell!$B$8*(1+((1+D$13)/(1+Modell!$B$10)-1))^Modell!$B$14))*((1+((1+D$13)/(1+Modell!$B$10)-1))^(1/12)-1)/(1-(1+((1+D$13)/(1+Modell!$B$10)-1))^(-($A18-Modell!$B$6))) -> 4357.5678 | E18: =((Modell!$B$8*(1+((1+E$13)/(1+Modell!$B$10)-1))^Modell!$B$14))*((1+((1+E$13)/(1+Modell!$B$10)-1))^(1/12)-1)/(1-(1+((1+E$13)/(1+Modell!$B$10)-1))^(-($A18-Modell!$B$6))) -> 7312.4036 | F18: =((Modell!$B$8*(1+((1+F$13)/(1+Modell!$B$10)-1))^Modell!$B$14))*((1+((1+F$13)/(1+Modell!$B$10)-1))^(1/12)-1)/(1-(1+((1+F$13)/(1+Modell!$B$10)-1))^(-($A18-Modell!$B$6))) -> 12089.738
A20: FAUSTREGEL – Netto-Monatsrente je 1.000 € heute investiert (€/Monat)
A21: Geld reicht bis Alter | B21: Auszahljahre | C21: 0.05 | D21: 0.06 | E21: 0.07 | F21: 0.08
A22: 85 | B22: =A22-Modell!$B$6 -> 20 | C22: =C6/Modell!$B$8*1000 -> 10.670028 | D22: =D6/Modell!$B$8*1000 -> 16.610671 | E22: =E6/Modell!$B$8*1000 -> 25.78164 | F22: =F6/Modell!$B$8*1000 -> 39.862608
A23: 90 | B23: =A23-Modell!$B$6 -> 25 | C23: =C7/Modell!$B$8*1000 -> 8.848447 | D23: =D7/Modell!$B$8*1000 -> 14.007137 | E23: =E7/Modell!$B$8*1000 -> 22.08009 | F23: =F7/Modell!$B$8*1000 -> 34.631647
A24: 95 | B24: =A24-Modell!$B$6 -> 30 | C24: =C8/Modell!$B$8*1000 -> 7.6399137 | D24: =D8/Modell!$B$8*1000 -> 12.290444 | E24: =E8/Modell!$B$8*1000 -> 19.660165 | F24: =F8/Modell!$B$8*1000 -> 31.248587
A25: 100 | B25: =A25-Modell!$B$6 -> 35 | C25: =C9/Modell!$B$8*1000 -> 6.7816615 | D25: =D9/Modell!$B$8*1000 -> 11.080284 | E25: =E9/Modell!$B$8*1000 -> 17.971558 | F25: =F9/Modell!$B$8*1000 -> 28.917985
A26: 105 | B26: =A26-Modell!$B$6 -> 40 | C26: =C10/Modell!$B$8*1000 -> 6.1423024 | D26: =D10/Modell!$B$8*1000 -> 10.186468 | E26: =E10/Modell!$B$8*1000 -> 16.738987 | F26: =F10/Modell!$B$8*1000 -> 27.241745
A28: Lesart Faustregel: bei dieser Rendite/diesem Endalter bringt jede heute investierte 1.000 € rund den gezeigten Betrag reale Netto-Rente pro Monat – linear skalierbar.

Sheet Renteneintritt variabel
A1: Renteneintritt variabel – feste Annahmen, nur die Zeit bis zur Rente ändert sich
A2: Tod mit 90 und 7 % Rendite fix. n = Jahre bis Renteneintritt ist die einzige Variable.
A4: FESTE ANNAHMEN
A5: Aktuelles Alter | B5: 25
A6: Todesalter (fix) | B6: 90
A7: Rendite p.a. nominal (fix) | B7: 0.07
A8: Inflation p.a. (fix) | B8: 0.025
A9: Steuersatz effektiv (fix) | B9: 0.185
A10: Startkapital | B10: 300000
A12: KONSTANTEN
A13: Realzins brutto r | B13: =(1+B7)/(1+B8)-1 -> 0.043902439
A14: Nettorendite nominal i·(1-t) | B14: =B7*(1-B9) -> 0.05705
A15: Realzins netto r* (Entnahme) | B15: =(1+B14)/(1+B8)-1 -> 0.031268293
A16: Monatsfaktor q=(1+r*)^(1/12)-1 | B16: =(1+B15)^(1/12)-1 -> 0.0025690775
A18: Jahre bis Rente n | B18: Renteneintritt (Alter) | C18: Auszahljahre m | D18: Kapital real netto (€) | E18: Monatsrente netto real (€) | F18: je 1.000 € → €/Mon
A19: 10 | B19: =$B$5+A19 -> 35 | C19: =$B$6-B19 -> 55 | D19: =$B$10*(1+((1+$B$7)^A19-1)*(1-$B$9))/(1+$B$8)^A19 -> 419088.34 | E19: =D19*((1+$B$15)^(1/12)-1)/(1-(1+$B$15)^(-C19)) -> 1319.2714 | F19: =E19/$B$10*1000 -> 4.3975714
A20: 11 | B20: =$B$5+A20 -> 36 | C20: =$B$6-B20 -> 54 | D20: =$B$10*(1+((1+$B$7)^A20-1)*(1-$B$9))/(1+$B$8)^A20 -> 434526.41 | E20: =D20*((1+$B$15)^(1/12)-1)/(1-(1+$B$15)^(-C20)) -> 1377.5755 | F20: =E20/$B$10*1000 -> 4.5919184
A21: 12 | B21: =$B$5+A21 -> 37 | C21: =$B$6-B21 -> 53 | D21: =$B$10*(1+((1+$B$7)^A21-1)*(1-$B$9))/(1+$B$8)^A21 -> 450714.46 | E21: =D21*((1+$B$15)^(1/12)-1)/(1-(1+$B$15)^(-C21)) -> 1439.4293 | F21: =E21/$B$10*1000 -> 4.7980975
A22: 13 | B22: =$B$5+A22 -> 38 | C22: =$B$6-B22 -> 52 | D22: =$B$10*(1+((1+$B$7)^A22-1)*(1-$B$9))/(1+$B$8)^A22 -> 467683.67 | E22: =D22*((1+$B$15)^(1/12)-1)/(1-(1+$B$15)^(-C22)) -> 1505.0644 | F22: =E22/$B$10*1000 -> 5.0168812
A23: 14 | B23: =$B$5+A23 -> 39 | C23: =$B$6-B23 -> 51 | D23: =$B$10*(1+((1+$B$7)^A23-1)*(1-$B$9))/(1+$B$8)^A23 -> 485466.6 | E23: =D23*((1+$B$15)^(1/12)-1)/(1-(1+$B$15)^(-C23)) -> 1574.7318 | F23: =E23/$B$10*1000 -> 5.2491059
A24: 15 | B24: =$B$5+A24 -> 40 | C24: =$B$6-B24 -> 50 | D24: =$B$10*(1+((1+$B$7)^A24-1)*(1-$B$9))/(1+$B$8)^A24 -> 504097.31 | E24: =D24*((1+$B$15)^(1/12)-1)/(1-(1+$B$15)^(-C24)) -> 1648.7033 | F24: =E24/$B$10*1000 -> 5.4956778
A25: 16 | B25: =$B$5+A25 -> 41 | C25: =$B$6-B25 -> 49 | D25: =$B$10*(1+((1+$B$7)^A25-1)*(1-$B$9))/(1+$B$8)^A25 -> 523611.38 | E25: =D25*((1+$B$15)^(1/12)-1)/(1-(1+$B$15)^(-C25)) -> 1727.2742 | F25: =E25/$B$10*1000 -> 5.7575805
A26: 17 | B26: =$B$5+A26 -> 42 | C26: =$B$6-B26 -> 48 | D26: =$B$10*(1+((1+$B$7)^A26-1)*(1-$B$9))/(1+$B$8)^A26 -> 544045.99 | E26: =D26*((1+$B$15)^(1/12)-1)/(1-(1+$B$15)^(-C26)) -> 1810.7649 | F26: =E26/$B$10*1000 -> 6.0358829
A27: 18 | B27: =$B$5+A27 -> 43 | C27: =$B$6-B27 -> 47 | D27: =$B$10*(1+((1+$B$7)^A27-1)*(1-$B$9))/(1+$B$8)^A27 -> 565440.01 | E27: =D27*((1+$B$15)^(1/12)-1)/(1-(1+$B$15)^(-C27)) -> 1899.5245 | F27: =E27/$B$10*1000 -> 6.3317484
A28: 19 | B28: =$B$5+A28 -> 44 | C28: =$B$6-B28 -> 46 | D28: =$B$10*(1+((1+$B$7)^A28-1)*(1-$B$9))/(1+$B$8)^A28 -> 587834.03 | E28: =D28*((1+$B$15)^(1/12)-1)/(1-(1+$B$15)^(-C28)) -> 1993.9335 | F28: =E28/$B$10*1000 -> 6.646445
A29: 20 | B29: =$B$5+A29 -> 45 | C29: =$B$6-B29 -> 45 | D29: =$B$10*(1+((1+$B$7)^A29-1)*(1-$B$9))/(1+$B$8)^A29 -> 611270.48 | E29: =D29*((1+$B$15)^(1/12)-1)/(1-(1+$B$15)^(-C29)) -> 2094.4071 | F29: =E29/$B$10*1000 -> 6.9813571
A30: 21 | B30: =$B$5+A30 -> 46 | C30: =$B$6-B30 -> 44 | D30: =$B$10*(1+((1+$B$7)^A30-1)*(1-$B$9))/(1+$B$8)^A30 -> 635793.66 | E30: =D30*((1+$B$15)^(1/12)-1)/(1-(1+$B$15)^(-C30)) -> 2201.3997 | F30: =E30/$B$10*1000 -> 7.3379989
... A54: 45 | B54: =$B$5+A54 -> 70 | C54: =$B$6-B54 -> 20 | D54: =$B$10*(1+((1+$B$7)^A54-1)*(1-$B$9))/(1+$B$8)^A54 -> 1708612.5 | E54: =D54*((1+$B$15)^(1/12)-1)/(1-(1+$B$15)^(-C54)) -> 9546.9808 | F54: =E54/$B$10*1000 -> 31.823269
A56: FORMEL (netto, real, heutige Kaufkraft):
A57: Rente(n) = K(n) · q / ( 1 − (1+r*)^(−m) )
A58: K(n) = P · [ 1 + ( (1+i)^n − 1 ) · (1−t) ] / (1+π)^n (reales Netto-Kapital bei Renteneintritt)
A59: r* = (1 + i·(1−t)) / (1+π) − 1 = 3,1268 % q = (1+r*)^(1/12) − 1 = 0,2569 %/Monat
A60: m = Todesalter − Alter − n = 90 − 25 − n = 65 − n (Auszahljahre)
A61: fix: i = 7 %, π = 2,5 %, t = 18,5 %, P = Startkapital
A62: Je 1.000 €: einfach P = 1000 setzen (Ergebnis ist linear in P).
